{
	"id": "CqXgY2J2DRDtYnB",
	"json": "{\"id\":\"CqXgY2J2DRDtYnB\",\"url\":\"https://www.spacemanmusic.com/product/crumar-stratus-synth/\",\"loadedUrl\":\"https://www.spacemanmusic.com/product/crumar-stratus-synth/\",\"uniqueKey\":\"https://www.spacemanmusic.com/product/crumar-stratus-synth\",\"method\":\"GET\",\"noRetry\":false,\"retryCount\":0,\"errorMessages\":[],\"headers\":{},\"userData\":{\"label\":\"SM_DETAILS\"},\"handledAt\":\"2023-01-16T21:45:50.851Z\"}",
	"method": "GET",
	"orderNo": null,
	"retryCount": 0,
	"uniqueKey": "https://www.spacemanmusic.com/product/crumar-stratus-synth",
	"url": "https://www.spacemanmusic.com/product/crumar-stratus-synth/"
}