{
	"uid": "hWihCneeAljEEqoMW98dja+cBlc=",
	"title": "Kickall (Used)",
	"description": "A straightforward, no nonsense, all-analog kick generator from Befaco.\n\nKickall is a 6HP compact synth voice that features everything needed to make a big fat Kick sound. A stable VCO that tracks V/Oct, a couple of VCAs, envelopes for volume and pitch and an aggressive waveshaper.\n\nThis used DIY model is in great condition and comes with a ribbon cable for power.",
	"price": 269,
	"shipping": null,
	"currency": "CAD",
	"site": "https://cicadasound.ca/",
	"url": "https://cicadasound.ca/collections/used/products/befaco-kickall-used",
	"posted": "2022-10-06T17:15:45.000Z",
	"tags": [
		"Kickall",
		"(Used)"
	],
	"inStock": true
}