{
	"uid": "BHadll6VPKfyOy8vy2+taG+RA10=",
	"title": "Kurzweil K2500X",
	"description": "Year Released: 1996\nKeyboard: 88 keys with velocity and aftertouch\nPolyphony: 48 notes\nMultitimbral: 16 parts\nPreset Patches: 199\nPreset Performances: 100\nROM: 8MB (Expandable to 28MB)\nEffects: 31 programmable DSP effects",
	"price": 749,
	"shipping": null,
	"currency": "CAD",
	"site": "https://spacemanmusic.com/",
	"url": "https://www.spacemanmusic.com/product/kurzweil-k2500x/",
	"posted": null,
	"tags": [
		"Kurzweil",
		"K2500X"
	],
	"inStock": true
}