{
	"uid": "Mfe+dwxK9nUQ2HnzTd4DPwfZlVA=",
	"title": "Korg MS-20 FS",
	"description": "The legendary 1978 Korg MS-20 analog synthesizer reborn\n1/4″ jack patchbay\nProvides powerful vintage sound, from deep, growling basses to crisp, rounded leads\n2 oscillators with ring modulation\nEnvelope generators with delay and hold\nVCA maintains the original basic design, but with reduced noise\nEarly- and late-model filters (highpass/lowpass with peak/resonance) capable of self-oscillation\nESP utilizes the pitch or volume of an external audio source to control the synthesizer\n37-note keyboard\nMIDI in and USB connector provides keyboard and DAW MIDI connectivity",
	"price": 1499,
	"shipping": null,
	"currency": "CAD",
	"site": "https://spacemanmusic.com/",
	"url": "https://www.spacemanmusic.com/product/korg-ms-20-fs/",
	"posted": null,
	"tags": [
		"Korg",
		"MS-20",
		"FS"
	],
	"inStock": true
}